cogency/__init__.py
cogency/agent.py
cogency/replay.py
cogency/resume.py
cogency/context/__init__.py
cogency/context/assembly.py
cogency/context/conversation.py
cogency/context/profile.py
cogency/context/system.py
cogency/core/__init__.py
cogency/core/accumulator.py
cogency/core/circuit.py
cogency/core/codec.py
cogency/core/config.py
cogency/core/errors.py
cogency/core/executor.py
cogency/core/parser.py
cogency/core/protocols.py
cogency/core/registry.py
cogency/core/security.py
cogency/core/tool.py
cogency/lib/__init__.py
cogency/lib/debug.py
cogency/lib/metrics.py
cogency/lib/resilience.py
cogency/lib/sqlite.py
cogency/lib/telemetry.py
cogency/lib/uuid7.py
cogency/lib/llms/__init__.py
cogency/lib/llms/anthropic.py
cogency/lib/llms/gemini.py
cogency/lib/llms/interrupt.py
cogency/lib/llms/openai.py
cogency/lib/llms/rotation.py
cogency/tools/__init__.py
cogency/tools/edit.py
cogency/tools/find.py
cogency/tools/list.py
cogency/tools/read.py
cogency/tools/recall.py
cogency/tools/replace.py
cogency/tools/scrape.py
cogency/tools/search.py
cogency/tools/shell.py
cogency/tools/write.py
cogency-3.3.0.dist-info/METADATA
cogency-3.3.0.dist-info/WHEEL
cogency-3.3.0.dist-info/entry_points.txt
cogency-3.3.0.dist-info/licenses/LICENSE
cogency-3.3.0.dist-info/RECORD
