Metadata-Version: 2.4
Name: cogency
Version: 3.3.0
Summary: Streaming agents
Project-URL: homepage, https://github.com/iteebz/cogency
Project-URL: repository, https://github.com/iteebz/cogency
Author-email: Tyson Chan <tyson.chan@proton.me>
License-Expression: Apache-2.0
License-File: LICENSE
Keywords: agents,ai,cognition,memory,react,reasoning,streaming,tools,tracing
Classifier: Development Status :: 5 - Production/Stable
Classifier: Intended Audience :: Developers
Classifier: License :: OSI Approved :: Apache Software License
Classifier: Programming Language :: Python :: 3
Classifier: Programming Language :: Python :: 3.11
Classifier: Programming Language :: Python :: 3.12
Classifier: Topic :: Scientific/Engineering :: Artificial Intelligence
Classifier: Topic :: Software Development :: Libraries :: Python Modules
Requires-Python: <3.13,>=3.11
Requires-Dist: anthropic>=0.67.0
Requires-Dist: ddgs>=9.5.2
Requires-Dist: google-api-core>=2.11.0
Requires-Dist: google-genai>=1.36.0
Requires-Dist: openai>=1.107.1
Requires-Dist: python-dotenv>=1.0.0
Requires-Dist: tiktoken>=0.11.0
Requires-Dist: trafilatura>=2.0.0
Requires-Dist: typer>=0.17.4
Requires-Dist: websockets==15.0.0
